{
    "profiles": [
        {
            "name": "Default profile",
            "selected": true,
            "virtual_hid_keyboard": { "keyboard_type_v2": "jis" },
            "simple_modifications": [
                {
                    "from": { "key_code": "caps_lock" },
                    "to": [{ "key_code": "left_control" }]
                },
                {
                    "from": { "key_code": "left_control" },
                    "to": [{ "key_code": "caps_lock" }]
                }
            ],
            "complex_modifications": {
                "rules": [
                    {
                        "description": "Swap 짜 and \\: 짜 outputs \\, option+짜 outputs 짜",
                        "manipulators": [
                            {
                                "type": "basic",
                                "from": {
                                    "key_code": "international3",
                                    "modifiers": { "mandatory": ["option"] }
                                },
                                "to": [{ "key_code": "international3" }]
                            },
                            {
                                "type": "basic",
                                "from": { "key_code": "international3" },
                                "to": [
                                    {
                                        "key_code": "international3",
                                        "modifiers": ["option"]
                                    }
                                ]
                            }
                        ]
                    },
                    {
                        "description": "Map shift+enter to option+enter",
                        "manipulators": [
                            {
                                "type": "basic",
                                "from": {
                                    "key_code": "return_or_enter",
                                    "modifiers": { "mandatory": ["shift"] }
                                },
                                "to": [
                                    {
                                        "key_code": "return_or_enter",
                                        "modifiers": ["option"]
                                    }
                                ]
                            }
                        ]
                    }
                ]
            }
        }
    ]
}
